dataArtist/functions.py
dataArtist/gui.py
dataArtist/gui_asServer.py
dataArtist/gui_noInstall.py
dataArtist/__init__.py
dataArtist/components/RabbitMQServer.py
dataArtist/components/WatchFolder.py
dataArtist/components/__init__.py
dataArtist/figures/DisplayWidget.py
dataArtist/figures/_PyqtgraphgDisplayBase.py
dataArtist/figures/_view3d.py
dataArtist/figures/__init__.py
dataArtist/figures/image/ImageWidget.py
dataArtist/figures/image/__init__.py
dataArtist/figures/image/tools/__init__.py
dataArtist/figures/image/tools/calibrate/DarkCurrent.py
dataArtist/figures/image/tools/calibrate/DeconvolutionBalance.py
dataArtist/figures/image/tools/calibrate/FlatField.py
dataArtist/figures/image/tools/calibrate/LensDistortion.py
dataArtist/figures/image/tools/calibrate/NoiseLevelFunction.py
dataArtist/figures/image/tools/calibrate/PointSpreadFunction.py
dataArtist/figures/image/tools/calibrate/RelativeSharpness.py
dataArtist/figures/image/tools/calibrate/__init__.py
dataArtist/figures/image/tools/correct/CorrectCamera.py
dataArtist/figures/image/tools/correct/Move.py
dataArtist/figures/image/tools/correct/PatternRecognition.py
dataArtist/figures/image/tools/correct/PerspectiveCorrection.py
dataArtist/figures/image/tools/correct/ScaleHistogram.py
dataArtist/figures/image/tools/correct/Stitch.py
dataArtist/figures/image/tools/correct/__init__.py
dataArtist/figures/image/tools/draw/Arrow.py
dataArtist/figures/image/tools/draw/Freehand.py
dataArtist/figures/image/tools/draw/Text.py
dataArtist/figures/image/tools/draw/__init__.py
dataArtist/figures/image/tools/filter/CV2Denoise.py
dataArtist/figures/image/tools/filter/EdgeDetection.py
dataArtist/figures/image/tools/filter/ExtractBackground.py
dataArtist/figures/image/tools/filter/FourierFilter.py
dataArtist/figures/image/tools/filter/MedianFilterThreshold.py
dataArtist/figures/image/tools/filter/SimpleFilter.py
dataArtist/figures/image/tools/filter/ZDenoise.py
dataArtist-0.1.15.dist-info/DESCRIPTION.rst
dataArtist-0.1.15.dist-info/entry_points.txt
dataArtist-0.1.15.dist-info/METADATA
dataArtist-0.1.15.dist-info/metadata.json
dataArtist-0.1.15.dist-info/RECORD
dataArtist-0.1.15.dist-info/top_level.txt
dataArtist-0.1.15.dist-info/WHEEL
