Metadata-Version: 2.0
Name: dataArtist
Version: 0.1.15
Summary: 
Requires-Dist: fancytools
Requires-Dist: fancywidgets
Requires-Dist: appbase
Requires-Dist: imgProcessor
Requires-Dist: pyqtgraph-karl
Requires-Dist: puka
Requires-Dist: numpy
Requires-Dist: scipy
Requires-Dist: scikit-image
Requires-Dist: lxml
Requires-Dist: transforms3d
Requires-Dist: cssselect
Requires-Dist: hachoir-core
Requires-Dist: hachoir-metadata
Requires-Dist: hachoir-parser
Requires-Dist: exifread
Requires-Dist: pygments
Requires-Dist: tifffile
Requires-Dist: enum34
